Progetto_One_Pin_Keypad-0.0.2.dist-info/DESCRIPTION.rst
Progetto_One_Pin_Keypad-0.0.2.dist-info/METADATA
Progetto_One_Pin_Keypad-0.0.2.dist-info/RECORD
Progetto_One_Pin_Keypad-0.0.2.dist-info/WHEEL
Progetto_One_Pin_Keypad-0.0.2.dist-info/dependency_links.txt
Progetto_One_Pin_Keypad-0.0.2.dist-info/metadata.json
Progetto_One_Pin_Keypad-0.0.2.dist-info/top_level.txt
onepinkeypad/__init__.py
onepinkeypad/onepinkeypad.py
