Metadata-Version: 2.0
Name: Progetto-One-Pin-Keypad
Version: 0.0.2
Summary: Raspberry Pi compatible Python Package with examples for the One Pin Keypad.
Home-page: https://github.com/ProgettoCompany/Progetto_One_Pin_Keypad_Python_Package
Author: Progetto Company
Author-email: progettocompany@gmail.com
License: MIT
Platform: UNKNOWN
Classifier: Operating System :: POSIX :: Linux
Classifier: License :: OSI Approved :: MIT License
Classifier: Intended Audience :: Developers
Classifier: Programming Language :: Python :: 3
Classifier: Topic :: Software Development
Classifier: Topic :: System :: Hardware
Requires-Dist: adafruit-circuitpython-ads1x15 (>=1.0.2)
